structural_arithmetic_modules/adder/adder_ripple_carry.v
// ============================================================
// adder_ripple_carry.v
// ============================================================
// N sets the operand and sum width, must be >= 1
module adder_ripple_carry #(parameter integer N = 128)(a, b, carry_in, sum, carry_out);

    input   [N-1:0] a;
    input   [N-1:0] b;
    input           carry_in;
    output  [N-1:0] sum;
    output          carry_out;

    wire [N:0] carry;

    assign carry[0] = carry_in;

    genvar i;

    generate
        for (i = 0; i < N; i = i + 1) begin : ripple_carry
            assign sum[i] = a[i] ^ b[i] ^ carry[i];
            assign carry[i+1] = (a[i] & b[i]) | (a[i] & carry[i]) | (b[i] & carry[i]);
        end
    endgenerate

    assign carry_out = carry[N];

endmodule

structural_arithmetic_modules/test/adder_ripple_carry_test.v
`timescale 1ns / 1ps

module adder_test #(parameter integer N = 8); // Change N here
    localparam [N-1:0] ONE = 1;
    localparam [N-1:0] FIVE = 5;
    localparam [N-1:0] THREE = 3;
    localparam [N-1:0] MAX_VALUE = {N{1'b1}};
    localparam [N-1:0] SIGN_BIT = 1 << (N-1);
    
    // Truncating the repeated pair also supports odd widths.
    localparam [N-1:0] ALTERNATING = {N{2'b10}};
    localparam [N:0] BASIC_SUM = {1'b0, FIVE} + {1'b0, THREE};
    localparam [N:0] BASIC_SUM_CIN = BASIC_SUM + 1'b1;

    reg  [N-1:0] a;
    reg  [N-1:0] b;
    reg          carry_in;
    wire [N-1:0] sum;
    wire         carry_out;

    integer errors;

    adder_ripple_carry #(.N(N)) dut (
        .a(a),
        .b(b),
        .carry_in(carry_in),
        .sum(sum),
        .carry_out(carry_out)
    );

    // PASS/FAIL message
    task check;
        input [255:0] test_name;
        input [N-1:0] expected;
        input         expected_carry;
        begin
            #1;
            if ((sum !== expected) ||
                (carry_out !== expected_carry)) begin
                errors = errors + 1;
                $display("FAIL: test=%s a=%h b=%h carry_in=%b expected sum=%h carry_out=%b got sum=%h carry_out=%b",
                         test_name, a, b, carry_in, expected, expected_carry,
                         sum, carry_out);
            end else begin
                $display("PASS: test=%s a=%h b=%h carry_in=%b sum=%h carry_out=%b",
                         test_name, a, b, carry_in, sum, carry_out);
            end
        end
    endtask

    initial begin
        $dumpfile("test/waves/adder.vcd");
        $dumpvars(0, adder_test);

        errors = 0;
        if (N < 1) $fatal(1, "N must be at least 1.");

        // ADD: 5 + 3 (operands truncate to N bits for small widths)
        a = FIVE;
        b = THREE;
        carry_in = 1'b0;
        check("ADD", BASIC_SUM[N-1:0], BASIC_SUM[N]);

        // ADD: carry in
        a = 5;
        b = 3;
        carry_in = 1'b1;
        check("ADD + carry in", BASIC_SUM_CIN[N-1:0], BASIC_SUM_CIN[N]);

        // ADD: zero operands
        a = 0;
        b = 0;
        carry_in = 1'b0;
        check("ADD zero", 0, 1'b0);

        // ADD: carry in with zero operands
        a = 0;
        b = 0;
        carry_in = 1'b1;
        check("ADD zero + carry in", ONE, 1'b0);

        // ADD: maximum value without carry out
        a = MAX_VALUE;
        b = 0;
        carry_in = 1'b0;
        check("ADD maximum", MAX_VALUE, 1'b0);

        // ADD: carry propagates through all N bits
        a = MAX_VALUE;
        b = 1;
        carry_in = 1'b0;
        check("ADD + carry out", 0, 1'b1);

        // ADD: carry in propagates through all N bits
        a = MAX_VALUE;
        b = 0;
        carry_in = 1'b1;
        check("ADD carry in + carry out", 0, 1'b1);

        // ADD: two maximum operands
        a = MAX_VALUE;
        b = MAX_VALUE;
        carry_in = 1'b0;
        check("ADD two maximums", (MAX_VALUE - 1), 1'b1);

        // ADD: two maximum operands with carry in
        a = MAX_VALUE;
        b = MAX_VALUE;
        carry_in = 1'b1;
        check("ADD maximums + carry in", MAX_VALUE, 1'b1);

        // ADD: signed boundary (the adder has no overflow output)
        a = (SIGN_BIT - 1);
        b = 1;
        carry_in = 1'b0;
        check("ADD signed boundary", SIGN_BIT, 1'b0);

        // ADD: complementary alternating bits
        a = ALTERNATING;
        b = ~ALTERNATING;
        carry_in = 1'b0;
        check("ADD alternating bits", MAX_VALUE, 1'b0);

        if (errors == 0) begin
            $display("All adder tests passed.");
        end else begin
            $fatal(1, "Adder tests failed with %0d error(s).", errors);
        end

        $finish;
    end
endmodule

structural_arithmetic_modules/test/waves/adder.vcd
$date
	Sat Sep 12 10:28:17 2026
$end
$version
	Icarus Verilog
$end
$timescale
	1ps
$end
$scope module adder_test $end
$var wire 8 ! sum [7:0] $end
$var wire 1 " carry_out $end
$var parameter 8 # ALTERNATING $end
$var parameter 9 $ BASIC_SUM $end
$var parameter 9 % BASIC_SUM_CIN $end
$var parameter 8 & FIVE $end
$var parameter 8 ' MAX_VALUE $end
$var parameter 32 ( N $end
$var parameter 8 ) ONE $end
$var parameter 8 * SIGN_BIT $end
$var parameter 8 + THREE $end
$var reg 8 , a [7:0] $end
$var reg 8 - b [7:0] $end
$var reg 1 . carry_in $end
$var integer 32 / errors [31:0] $end
$scope module dut $end
$var wire 8 0 a [7:0] $end
$var wire 8 1 b [7:0] $end
$var wire 1 . carry_in $end
$var wire 8 2 sum [7:0] $end
$var wire 1 " carry_out $end
$var wire 9 3 carry [8:0] $end
$var parameter 32 4 N $end
$scope begin ripple_carry[0] $end
$var parameter 2 5 i $end
$upscope $end
$scope begin ripple_carry[1] $end
$var parameter 2 6 i $end
$upscope $end
$scope begin ripple_carry[2] $end
$var parameter 3 7 i $end
$upscope $end
$scope begin ripple_carry[3] $end
$var parameter 3 8 i $end
$upscope $end
$scope begin ripple_carry[4] $end
$var parameter 4 9 i $end
$upscope $end
$scope begin ripple_carry[5] $end
$var parameter 4 : i $end
$upscope $end
$scope begin ripple_carry[6] $end
$var parameter 4 ; i $end
$upscope $end
$scope begin ripple_carry[7] $end
$var parameter 4 < i $end
$upscope $end
$upscope $end
$scope task check $end
$var reg 8 = expected [7:0] $end
$var reg 1 > expected_carry $end
$var reg 256 ? test_name [255:0] $end
$upscope $end
$upscope $end
$enddefinitions $end
$comment Show the parameter values. $end
$dumpall
b111 <
b110 ;
b101 :
b100 9
b11 8
b10 7
b1 6
b0 5
b1000 4
b11 +
b10000000 *
b1 )
b1000 (
b11111111 '
b101 &
b1001 %
b1000 $
b10101010 #
$end
#0
$dumpvars
b10000010100010001000100 ?
0>
b1000 =
b1110 3
b1000 2
b11 1
b101 0
b0 /
0.
b11 -
b101 ,
0"
b1000 !
$end
#1000
b1001 !
b1001 2
b1111 3
b1001 =
b100000101000100010001000010000000101011001000000110001101100001011100100111001001111001001000000110100101101110 ?
1.
#2000
b0 !
b0 2
b0 3
b0 =
b100000101000100010001000010000001111010011001010111001001101111 ?
0.
b0 -
b0 1
b0 ,
b0 0
#3000
b1 !
b1 2
b1 3
b1 =
b1000001010001000100010000100000011110100110010101110010011011110010000000101011001000000110001101100001011100100111001001111001001000000110100101101110 ?
1.
#4000
0"
b11111111 !
b11111111 2
b0 3
b11111111 =
b100000101000100010001000010000001101101011000010111100001101001011011010111010101101101 ?
0.
b11111111 ,
b11111111 0
#5000
1"
b111111110 3
b0 !
b0 2
1>
b0 =
b10000010100010001000100001000000010101100100000011000110110000101110010011100100111100100100000011011110111010101110100 ?
b1 -
b1 1
#6000
1"
b0 !
b0 2
b111111111 3
b10000010100010001000100001000000110001101100001011100100111001001111001001000000110100101101110001000000010101100100000011000110110000101110010011100100111100100100000011011110111010101110100 ?
1.
b0 -
b0 1
#7000
b11111110 !
b11111110 2
b111111110 3
b11111110 =
b1000001010001000100010000100000011101000111011101101111001000000110110101100001011110000110100101101101011101010110110101110011 ?
0.
b11111111 -
b11111111 1
#8000
b11111111 !
b11111111 2
b111111111 3
b11111111 =
b100000101000100010001000010000001101101011000010111100001101001011011010111010101101101011100110010000000101011001000000110001101100001011100100111001001111001001000000110100101101110 ?
1.
#9000
0"
b10000000 !
b10000000 2
b11111110 3
0>
b10000000 =
b1000001010001000100010000100000011100110110100101100111011011100110010101100100001000000110001001101111011101010110111001100100011000010111001001111001 ?
0.
b1 -
b1 1
b1111111 ,
b1111111 0
#10000
0"
b0 3
b11111111 !
b11111111 2
b11111111 =
b100000101000100010001000010000001100001011011000111010001100101011100100110111001100001011101000110100101101110011001110010000001100010011010010111010001110011 ?
b1010101 -
b1010101 1
b10101010 ,
b10101010 0
